ibd_parser/__init__.py
ibd_parser/cli.py
ibd_parser/constants.py
ibd_parser/parser.py
ibd_parser/utils.py
ibd_parser/page/__init__.py
ibd_parser/page/fil.py
ibd_parser/page/index.py
ibd_parser/record/__init__.py
ibd_parser/record/record_header.py
ibd_parser/record/record_parser.py
ibd_parser-0.1.5.dist-info/LICENSE
ibd_parser-0.1.5.dist-info/METADATA
ibd_parser-0.1.5.dist-info/WHEEL
ibd_parser-0.1.5.dist-info/entry_points.txt
ibd_parser-0.1.5.dist-info/top_level.txt
ibd_parser-0.1.5.dist-info/RECORD
