Metadata-Version: 2.1
Name: ibd-parser
Version: 0.1.5
Summary: A Python tool for parsing and analyzing InnoDB .ibd files
Author-email: likeyiyy <likeyiyying@gmail.com>
License: MIT
Project-URL: Homepage, https://github.com/likeyiyy/ibd-parser
Project-URL: Bug Tracker, https://github.com/likeyiyy/ibd-parser/issues
Project-URL: Documentation, https://github.com/likeyiyy/ibd-parser#README.md
Project-URL: Source Code, https://github.com/likeyiyy/ibd-parser
Keywords: mysql,innodb,ibd,parser,database
Classifier: Development Status :: 3 - Alpha
Classifier: Intended Audience :: Developers
Classifier: Programming Language :: Python :: 3
Classifier: Programming Language :: Python :: 3.7
Classifier: Programming Language :: Python :: 3.8
Classifier: Programming Language :: Python :: 3.9
Classifier: Programming Language :: Python :: 3.10
Classifier: License :: OSI Approved :: MIT License
Classifier: Operating System :: OS Independent
Classifier: Topic :: Database
Classifier: Topic :: Software Development :: Libraries :: Python Modules
Requires-Python: >=3.7
License-File: LICENSE
Requires-Dist: pyyaml>=6.0
Requires-Dist: tabulate>=0.9.0
Provides-Extra: dev
Requires-Dist: mysql-connector-python>=8.0.0; extra == "dev"
Requires-Dist: pytest>=7.0.0; extra == "dev"
Requires-Dist: bump2version>=1.0.0; extra == "dev"
Requires-Dist: build>=0.7.0; extra == "dev"
Requires-Dist: twine>=3.4.2; extra == "dev"
